pyeventic/__init__.py
pyeventic/awaitable_group.py
pyeventic/awaitable_group.pyi
pyeventic/event.py
pyeventic/event.pyi
pyeventic/py.typed
pyeventic-0.0.1.dist-info/METADATA
pyeventic-0.0.1.dist-info/WHEEL
pyeventic-0.0.1.dist-info/licenses/LICENSE
pyeventic-0.0.1.dist-info/RECORD
