Metadata-Version: 2.4
Name: pyeventic
Version: 0.0.1
Summary: A lightweight, strongly typed event library.
Project-URL: Homepage, https://github.com/TechnoBro03/Eventic
Project-URL: Issues, https://github.com/TechnoBro03/Eventic/issues
Project-URL: Wiki, https://github.com/TechnoBro03/Eventic/wiki
Author: TechnoBro03
License-Expression: MIT
License-File: LICENSE
Classifier: Operating System :: OS Independent
Classifier: Programming Language :: Python :: 3
Classifier: Typing :: Typed
Requires-Python: >=3.10
Provides-Extra: test
Requires-Dist: mypy; extra == 'test'
Requires-Dist: pytest; extra == 'test'
Requires-Dist: pytest-asyncio; extra == 'test'
Requires-Dist: pytest-cov; extra == 'test'
